libmdbx-0.3.1.dist-info/RECORD
libmdbx-0.3.1.dist-info/WHEEL
libmdbx-0.3.1.dist-info/METADATA
libmdbx-0.3.1.dist-info/licenses/LICENSE
mdbx/__init__.py
mdbx/mdbx.py
mdbx/lib/LICENSE
mdbx/lib/libmdbx.dylib
