Metadata-Version: 2.4
Name: libmdbx
Version: 0.3.1
Summary: The python bindings to libmdbx.
License-File: LICENSE
Keywords: mdbx,libmdbx,kvdb,bindings
Author: lazymio
Author-email: mio@lazym.io
Requires-Python: >=3.10,<4.0
Classifier: Programming Language :: Python :: 3
Classifier: Programming Language :: Python :: 3.10
Classifier: Programming Language :: Python :: 3.11
Classifier: Programming Language :: Python :: 3.12
Classifier: Programming Language :: Python :: 3.13
Classifier: Programming Language :: Python :: 3.14
Project-URL: Homepage, https://github.com/wtdcode/mdbx-py
